{"inputs":{"resources/css/component-note.css":{"bytes":459,"imports":[]},"resources/css/_fonts.css":{"bytes":187,"imports":[{"path":"https://fonts.gstatic.com/s/inter/v19/UcCm3FwrK3iLTcvnUwkT9nA2.woff2","kind":"url-token","external":true}]},"resources/css/_formatted-text.css":{"bytes":3421,"imports":[]},"resources/css/_reset.css":{"bytes":1330,"imports":[]},"resources/css/_variables.css":{"bytes":1299,"imports":[]},"resources/css/layout-common.css":{"bytes":3239,"imports":[{"path":"resources/css/_fonts.css","kind":"import-rule","original":"./_fonts.css"},{"path":"resources/css/_formatted-text.css","kind":"import-rule","original":"./_formatted-text.css"},{"path":"resources/css/_reset.css","kind":"import-rule","original":"./_reset.css"},{"path":"resources/css/_variables.css","kind":"import-rule","original":"./_variables.css"}]},"resources/css/layout-documentation-page.css":{"bytes":5004,"imports":[]},"resources/css/page-homepage.css":{"bytes":1123,"imports":[]},"resources/images/favicon.svg":{"bytes":307,"imports":[]},"resources/images/logo-bluesky.svg":{"bytes":757,"imports":[]},"resources/images/logo-discord.svg":{"bytes":1125,"imports":[]},"resources/images/logo-github.svg":{"bytes":796,"imports":[]},"resources/images/logo-linkedin.svg":{"bytes":1254,"imports":[]},"resources/images/logo-x.svg":{"bytes":405,"imports":[]},"resources/images/using-web-admin-panel/paddler-dashboard.avif":{"bytes":19780,"imports":[]},"resources/images/using-web-admin-panel/paddler-issues.avif":{"bytes":10877,"imports":[]},"resources/images/using-web-admin-panel/paddler-model-chat-template.avif":{"bytes":139615,"imports":[]},"resources/images/using-web-admin-panel/paddler-model-metadata.avif":{"bytes":73109,"imports":[]},"resources/images/using-web-admin-panel/paddler-model.avif":{"bytes":89542,"imports":[]},"resources/images/using-web-admin-panel/paddler-prompt.avif":{"bytes":113501,"imports":[]},"node_modules/idiomorph/dist/idiomorph.esm.js":{"bytes":47872,"imports":[],"format":"esm"},"resources/ts/global-live-reload.ts":{"bytes":979,"imports":[{"path":"node_modules/idiomorph/dist/idiomorph.esm.js","kind":"import-statement","original":"idiomorph"}],"format":"esm"}},"outputs":{"static/global-live-reload_V4HXASFF.js.map":{"imports":[],"exports":[],"inputs":{},"bytes":65469},"static/global-live-reload_V4HXASFF.js":{"imports":[],"exports":[],"entryPoint":"resources/ts/global-live-reload.ts","inputs":{"node_modules/idiomorph/dist/idiomorph.esm.js":{"bytesInOutput":24859},"resources/ts/global-live-reload.ts":{"bytesInOutput":881}},"bytes":25883},"static/logo-linkedin_WMRTI7JU.svg":{"imports":[],"exports":[],"inputs":{"resources/images/logo-linkedin.svg":{"bytesInOutput":1254}},"bytes":1254},"static/logo-linkedin_DHHT6E2B.js.map":{"imports":[],"exports":[],"inputs":{},"bytes":93},"static/logo-linkedin_DHHT6E2B.js":{"imports":[{"path":"static/logo-linkedin_WMRTI7JU.svg","kind":"file-loader"}],"exports":["default"],"entryPoint":"resources/images/logo-linkedin.svg","inputs":{"resources/images/logo-linkedin.svg":{"bytesInOutput":60}},"bytes":196},"static/logo-x_SFWBQEZU.svg":{"imports":[],"exports":[],"inputs":{"resources/images/logo-x.svg":{"bytesInOutput":405}},"bytes":405},"static/logo-x_SUVNC4UJ.js.map":{"imports":[],"exports":[],"inputs":{},"bytes":93},"static/logo-x_SUVNC4UJ.js":{"imports":[{"path":"static/logo-x_SFWBQEZU.svg","kind":"file-loader"}],"exports":["default"],"entryPoint":"resources/images/logo-x.svg","inputs":{"resources/images/logo-x.svg":{"bytesInOutput":46}},"bytes":161},"static/paddler-dashboard_D5YWHNXD.avif":{"imports":[],"exports":[],"inputs":{"resources/images/using-web-admin-panel/paddler-dashboard.avif":{"bytesInOutput":19780}},"bytes":19780},"static/paddler-dashboard_EHXG2VL2.js.map":{"imports":[],"exports":[],"inputs":{},"bytes":93},"static/paddler-dashboard_EHXG2VL2.js":{"imports":[{"path":"static/paddler-dashboard_D5YWHNXD.avif","kind":"file-loader"}],"exports":["default"],"entryPoint":"resources/images/using-web-admin-panel/paddler-dashboard.avif","inputs":{"resources/images/using-web-admin-panel/paddler-dashboard.avif":{"bytesInOutput":69}},"bytes":240},"static/paddler-issues_CUY5IQT5.avif":{"imports":[],"exports":[],"inputs":{"resources/images/using-web-admin-panel/paddler-issues.avif":{"bytesInOutput":10877}},"bytes":10877},"static/paddler-issues_7TXOLO4R.js.map":{"imports":[],"exports":[],"inputs":{},"bytes":93},"static/paddler-issues_7TXOLO4R.js":{"imports":[{"path":"static/paddler-issues_CUY5IQT5.avif","kind":"file-loader"}],"exports":["default"],"entryPoint":"resources/images/using-web-admin-panel/paddler-issues.avif","inputs":{"resources/images/using-web-admin-panel/paddler-issues.avif":{"bytesInOutput":63}},"bytes":225},"static/paddler-model-chat-template_T7YQFBHG.avif":{"imports":[],"exports":[],"inputs":{"resources/images/using-web-admin-panel/paddler-model-chat-template.avif":{"bytesInOutput":139615}},"bytes":139615},"static/paddler-model-chat-template_VXPOP4KE.js.map":{"imports":[],"exports":[],"inputs":{},"bytes":93},"static/paddler-model-chat-template_VXPOP4KE.js":{"imports":[{"path":"static/paddler-model-chat-template_T7YQFBHG.avif","kind":"file-loader"}],"exports":["default"],"entryPoint":"resources/images/using-web-admin-panel/paddler-model-chat-template.avif","inputs":{"resources/images/using-web-admin-panel/paddler-model-chat-template.avif":{"bytesInOutput":89}},"bytes":290},"static/paddler-model-metadata_FRMDAOYV.avif":{"imports":[],"exports":[],"inputs":{"resources/images/using-web-admin-panel/paddler-model-metadata.avif":{"bytesInOutput":73109}},"bytes":73109},"static/paddler-model-metadata_KNWDWF7R.js.map":{"imports":[],"exports":[],"inputs":{},"bytes":93},"static/paddler-model-metadata_KNWDWF7R.js":{"imports":[{"path":"static/paddler-model-metadata_FRMDAOYV.avif","kind":"file-loader"}],"exports":["default"],"entryPoint":"resources/images/using-web-admin-panel/paddler-model-metadata.avif","inputs":{"resources/images/using-web-admin-panel/paddler-model-metadata.avif":{"bytesInOutput":79}},"bytes":265},"static/paddler-model_FCXKTSHE.avif":{"imports":[],"exports":[],"inputs":{"resources/images/using-web-admin-panel/paddler-model.avif":{"bytesInOutput":89542}},"bytes":89542},"static/paddler-model_5Q2FAQDP.js.map":{"imports":[],"exports":[],"inputs":{},"bytes":93},"static/paddler-model_5Q2FAQDP.js":{"imports":[{"path":"static/paddler-model_FCXKTSHE.avif","kind":"file-loader"}],"exports":["default"],"entryPoint":"resources/images/using-web-admin-panel/paddler-model.avif","inputs":{"resources/images/using-web-admin-panel/paddler-model.avif":{"bytesInOutput":61}},"bytes":220},"static/paddler-prompt_WWSQZOGA.avif":{"imports":[],"exports":[],"inputs":{"resources/images/using-web-admin-panel/paddler-prompt.avif":{"bytesInOutput":113501}},"bytes":113501},"static/paddler-prompt_UTYICB3T.js.map":{"imports":[],"exports":[],"inputs":{},"bytes":93},"static/paddler-prompt_UTYICB3T.js":{"imports":[{"path":"static/paddler-prompt_WWSQZOGA.avif","kind":"file-loader"}],"exports":["default"],"entryPoint":"resources/images/using-web-admin-panel/paddler-prompt.avif","inputs":{"resources/images/using-web-admin-panel/paddler-prompt.avif":{"bytesInOutput":63}},"bytes":225},"static/favicon_MWST2DE3.svg":{"imports":[],"exports":[],"inputs":{"resources/images/favicon.svg":{"bytesInOutput":307}},"bytes":307},"static/favicon_N2MVOZXY.js.map":{"imports":[],"exports":[],"inputs":{},"bytes":93},"static/favicon_N2MVOZXY.js":{"imports":[{"path":"static/favicon_MWST2DE3.svg","kind":"file-loader"}],"exports":["default"],"entryPoint":"resources/images/favicon.svg","inputs":{"resources/images/favicon.svg":{"bytesInOutput":48}},"bytes":166},"static/logo-bluesky_SNSENXDG.svg":{"imports":[],"exports":[],"inputs":{"resources/images/logo-bluesky.svg":{"bytesInOutput":757}},"bytes":757},"static/logo-bluesky_4UHIYEXR.js.map":{"imports":[],"exports":[],"inputs":{},"bytes":93},"static/logo-bluesky_4UHIYEXR.js":{"imports":[{"path":"static/logo-bluesky_SNSENXDG.svg","kind":"file-loader"}],"exports":["default"],"entryPoint":"resources/images/logo-bluesky.svg","inputs":{"resources/images/logo-bluesky.svg":{"bytesInOutput":58}},"bytes":191},"static/logo-discord_MTSKQLP5.svg":{"imports":[],"exports":[],"inputs":{"resources/images/logo-discord.svg":{"bytesInOutput":1125}},"bytes":1125},"static/logo-discord_S2FNV4VY.js.map":{"imports":[],"exports":[],"inputs":{},"bytes":93},"static/logo-discord_S2FNV4VY.js":{"imports":[{"path":"static/logo-discord_MTSKQLP5.svg","kind":"file-loader"}],"exports":["default"],"entryPoint":"resources/images/logo-discord.svg","inputs":{"resources/images/logo-discord.svg":{"bytesInOutput":58}},"bytes":191},"static/logo-github_OFY5FFQM.svg":{"imports":[],"exports":[],"inputs":{"resources/images/logo-github.svg":{"bytesInOutput":796}},"bytes":796},"static/logo-github_EKJSZOUZ.js.map":{"imports":[],"exports":[],"inputs":{},"bytes":93},"static/logo-github_EKJSZOUZ.js":{"imports":[{"path":"static/logo-github_OFY5FFQM.svg","kind":"file-loader"}],"exports":["default"],"entryPoint":"resources/images/logo-github.svg","inputs":{"resources/images/logo-github.svg":{"bytesInOutput":56}},"bytes":186},"static/component-note_INB7HDKC.css.map":{"imports":[],"exports":[],"inputs":{},"bytes":898},"static/component-note_INB7HDKC.css":{"imports":[],"entryPoint":"resources/css/component-note.css","inputs":{"resources/css/component-note.css":{"bytesInOutput":457}},"bytes":552},"static/layout-common_RF6BEOJN.css.map":{"imports":[],"exports":[],"inputs":{},"bytes":15275},"static/layout-common_RF6BEOJN.css":{"imports":[{"path":"https://fonts.gstatic.com/s/inter/v19/UcCm3FwrK3iLTcvnUwkT9nA2.woff2","kind":"url-token","external":true}],"entryPoint":"resources/css/layout-common.css","inputs":{"resources/css/_fonts.css":{"bytesInOutput":181},"resources/css/_formatted-text.css":{"bytesInOutput":3335},"resources/css/_reset.css":{"bytesInOutput":1316},"resources/css/_variables.css":{"bytesInOutput":1297},"resources/css/layout-common.css":{"bytesInOutput":3017}},"bytes":9380},"static/layout-documentation-page_LN4FRK6E.css.map":{"imports":[],"exports":[],"inputs":{},"bytes":8307},"static/layout-documentation-page_LN4FRK6E.css":{"imports":[],"entryPoint":"resources/css/layout-documentation-page.css","inputs":{"resources/css/layout-documentation-page.css":{"bytesInOutput":4978}},"bytes":5095},"static/page-homepage_ITTBRKXK.css.map":{"imports":[],"exports":[],"inputs":{},"bytes":2012},"static/page-homepage_ITTBRKXK.css":{"imports":[],"entryPoint":"resources/css/page-homepage.css","inputs":{"resources/css/page-homepage.css":{"bytesInOutput":1115}},"bytes":1208}}}